odoo/addons/sale_order_lot_generator/README.rst
odoo/addons/sale_order_lot_generator/__init__.py
odoo/addons/sale_order_lot_generator/__manifest__.py
odoo/addons/sale_order_lot_generator/i18n/ca.po
odoo/addons/sale_order_lot_generator/i18n/de.po
odoo/addons/sale_order_lot_generator/i18n/el_GR.po
odoo/addons/sale_order_lot_generator/i18n/es.po
odoo/addons/sale_order_lot_generator/i18n/es_ES.po
odoo/addons/sale_order_lot_generator/i18n/es_VE.po
odoo/addons/sale_order_lot_generator/i18n/fi.po
odoo/addons/sale_order_lot_generator/i18n/fr.po
odoo/addons/sale_order_lot_generator/i18n/hr.po
odoo/addons/sale_order_lot_generator/i18n/hr_HR.po
odoo/addons/sale_order_lot_generator/i18n/hu.po
odoo/addons/sale_order_lot_generator/i18n/it.po
odoo/addons/sale_order_lot_generator/i18n/nl.po
odoo/addons/sale_order_lot_generator/i18n/nl_NL.po
odoo/addons/sale_order_lot_generator/i18n/pt.po
odoo/addons/sale_order_lot_generator/i18n/pt_BR.po
odoo/addons/sale_order_lot_generator/i18n/ro.po
odoo/addons/sale_order_lot_generator/i18n/sale_order_lot_generator.pot
odoo/addons/sale_order_lot_generator/i18n/sk.po
odoo/addons/sale_order_lot_generator/i18n/sl.po
odoo/addons/sale_order_lot_generator/i18n/tr.po
odoo/addons/sale_order_lot_generator/i18n/tr_TR.po
odoo/addons/sale_order_lot_generator/i18n/vi_VN.po
odoo/addons/sale_order_lot_generator/i18n/zh_CN.po
odoo/addons/sale_order_lot_generator/models/__init__.py
odoo/addons/sale_order_lot_generator/models/product_template.py
odoo/addons/sale_order_lot_generator/models/sale_order.py
odoo/addons/sale_order_lot_generator/models/sale_order_line.py
odoo/addons/sale_order_lot_generator/readme/CONFIGURE.md
odoo/addons/sale_order_lot_generator/readme/CONTRIBUTORS.md
odoo/addons/sale_order_lot_generator/readme/DESCRIPTION.md
odoo/addons/sale_order_lot_generator/readme/USAGE.md
odoo/addons/sale_order_lot_generator/static/description/icon.png
odoo/addons/sale_order_lot_generator/static/description/index.html
odoo_addon_sale_order_lot_generator-17.0.1.0.0.2.dist-info/METADATA
odoo_addon_sale_order_lot_generator-17.0.1.0.0.2.dist-info/WHEEL
odoo_addon_sale_order_lot_generator-17.0.1.0.0.2.dist-info/top_level.txt
odoo_addon_sale_order_lot_generator-17.0.1.0.0.2.dist-info/RECORD
